{
  "activity-list": [
    {
      "id": 1000,
      "createTime": "2009.10.13 11:14:27",
      "desc": "gyix",
      "activityType": 1,
      "bannerName": "kqj"
    },
    {
      "id": 1001,
      "createTime": "2001.11.14 23:43:14",
      "desc": "smioyrdsod",
      "activityType": 1,
      "bannerName": "mmot"
    },
    {
      "id": 1002,
      "createTime": "1973.10.28 18:54:43",
      "desc": "quou",
      "activityType": 1,
      "bannerName": "ygpbdm"
    },
    {
      "id": 1003,
      "createTime": "2008.02.07 00:46:04",
      "desc": "fhzoar",
      "activityType": 1,
      "bannerName": "zdt"
    },
    {
      "id": 1004,
      "createTime": "1994.06.03 10:55:53",
      "desc": "vgdfeg",
      "activityType": 1,
      "bannerName": "yqhqr"
    },
    {
      "id": 1005,
      "createTime": "2009.11.18 19:50:41",
      "desc": "lcvnrv",
      "activityType": 1,
      "bannerName": "ueioo"
    },
    {
      "id": 1006,
      "createTime": "1978.03.02 13:45:54",
      "desc": "otvu",
      "activityType": 1,
      "bannerName": "begcw"
    },
    {
      "id": 1007,
      "createTime": "2002.04.07 13:33:13",
      "desc": "okrxvbbxw",
      "activityType": 1,
      "bannerName": "kkanwh"
    },
    {
      "id": 1008,
      "createTime": "1970.11.06 12:18:17",
      "desc": "rccucdz",
      "activityType": 1,
      "bannerName": "pqnlpo"
    },
    {
      "id": 1009,
      "createTime": "1991.09.17 15:28:18",
      "desc": "ggnkpp",
      "activityType": 1,
      "bannerName": "izs"
    }
  ],
  "posts": [
    {
      "id": 1,
      "title": "json-server",
      "author": "typicode"
    }
  ]
}
